aioabcpapi/__init__.py
aioabcpapi/abcp.py
aioabcpapi/api.py
aioabcpapi/base.py
aioabcpapi/exceptions.py
aioabcpapi/cp/__init__.py
aioabcpapi/cp/admin.py
aioabcpapi/cp/base.py
aioabcpapi/cp/client.py
aioabcpapi/ts/__init__.py
aioabcpapi/ts/admin.py
aioabcpapi/ts/base.py
aioabcpapi/ts/client.py
aioabcpapi/utils/__init__.py
aioabcpapi/utils/fields_checker.py
aioabcpapi/utils/payload.py
aioabcpapi-2.2.0.dist-info/licenses/LICENSE
aioabcpapi-2.2.0.dist-info/METADATA
aioabcpapi-2.2.0.dist-info/WHEEL
aioabcpapi-2.2.0.dist-info/top_level.txt
aioabcpapi-2.2.0.dist-info/RECORD
