Metadata-Version: 2.4
Name: aioabcpapi
Version: 2.2.0
Summary: Асинхронная библиотека для ABCP API
Home-page: https://github.com/bl4ckm45k/aioabcpapi
Author: bl4ckm45k
Author-email: nonpowa@gmail.com
License: MIT
Project-URL: Documentation, https://www.abcp.ru/wiki/ABCP.API
Project-URL: Issue Tracker, https://github.com/bl4ckm45k/aioabcpapi/issues
Keywords: abcp,api,asyncio,aiohttp,async,wrapper
Classifier: Programming Language :: Python :: 3.10
Classifier: Programming Language :: Python :: 3.11
Classifier: Programming Language :: Python :: 3.12
Classifier: Programming Language :: Python :: 3.13
Classifier: Framework :: AsyncIO
Classifier: Intended Audience :: Developers
Classifier: License :: OSI Approved :: MIT License
Classifier: Operating System :: OS Independent
Classifier: Topic :: Software Development :: Libraries :: Application Frameworks
Requires-Python: >=3.10
License-File: LICENSE
Requires-Dist: aiohttp<4.0.0,>=3.10.11
Requires-Dist: certifi>=2023.7.22
Requires-Dist: ujson>=5.7.0
Requires-Dist: pytz>=2022.7.1
Requires-Dist: pyRFC3339>=1.1
Requires-Dist: wheel>=0.38.4
Dynamic: author
Dynamic: author-email
Dynamic: classifier
Dynamic: description
Dynamic: description-content-type
Dynamic: home-page
Dynamic: keywords
Dynamic: license
Dynamic: license-file
Dynamic: project-url
Dynamic: requires-dist
Dynamic: requires-python
Dynamic: summary
